{"f1_macro": 0.5705755470269, "f1_weighted": 0.6253785804921959, "precision_macro": 0.5996373433417836, "precision_weighted": 0.6309086545838134, "recall_macro": 0.5620686459597506, "recall_weighted": 0.6374458874458875, "accuracy": 0.6374458874458875, "class_scores": {"Southern Russians": 0.6903137789904502, "Ukranians": 0.40293040293040294, "Northen Russians": 0.7495961227786753, "Belarusians": 0.43946188340807174}, "skipped_nodes": 1, "memory_allocated_MB": 22.2958984375, "memory_reserved_MB": 138.0, "f1_macro_score_only_mask_connect": -100.0, "f1_macro_score_only_not_mask_connect": -100.0, "f1_macro_score_mixed_connect": -100.0, "only_mask_connect_sum": -100.0, "only_not_mask_connect_sum": -100.0, "mixed_connect_sum": -100.0, "model_name": "GL_TAGConv_3l_128h_w_k3"}