{"f1_macro": 0.32565284178187404, "f1_weighted": 0.44530891535499834, "precision_macro": 0.2756798756798757, "precision_weighted": 0.37694157694157693, "recall_macro": 0.39883831555755844, "recall_weighted": 0.5454545454545454, "accuracy": 0.5454545454545454, "class_scores": {"Southern Russians": 0.5714285714285714, "Ukranians": 0.0, "Northen Russians": 0.7311827956989247, "Belarusians": 0.0}, "skipped_nodes": 1, "memory_allocated_MB": 16.6328125, "memory_reserved_MB": 154.0, "model_name": "GL_GCNConv_3l_128h_w"}