{"f1_macro": 0.48081749722495154, "f1_weighted": 0.5485805749578012, "precision_macro": 0.4899817985045258, "precision_weighted": 0.5404625546443729, "recall_macro": 0.4864193661529036, "recall_weighted": 0.5686486486486486, "accuracy": 0.5686486486486486, "class_scores": {"Southern Russians": 0.6026587887740029, "Ukranians": 0.2231404958677686, "Northen Russians": 0.7366863905325444, "Belarusians": 0.3607843137254902}, "skipped_nodes": 0, "memory_allocated_MB": 97.5341796875, "memory_reserved_MB": 338.0, "f1_macro_score_only_mask_connect": 0.38095238095238093, "f1_macro_score_only_not_mask_connect": 1.0, "f1_macro_score_mixed_connect": 0.47551244531796377, "only_mask_connect_sum": 16.0, "only_not_mask_connect_sum": 1.0, "mixed_connect_sum": 908.0, "model_name": "GL_SAGEConv_9l_512h_de"}