{"f1_macro": 0.38405180912944886, "f1_weighted": 0.4344062514734943, "precision_macro": 0.373364903026428, "precision_weighted": 0.4316554079098558, "recall_macro": 0.46986928104575165, "recall_weighted": 0.5217391304347826, "accuracy": 0.5217391304347826, "class_scores": {"Chechens": 0.6938775510204082, "Kabardians, Circassians, Adyghes": 0.0, "Karachays, Balkars": 0.5079365079365079, "Ingush": 0.5, "Dagestan peoples": 0.7619047619047619, "Ossetians": 0.6086956521739131, "Kumyks": 0.0, "Nogais": 0.0}, "skipped_nodes": 3, "memory_allocated_MB": 102.76220703125, "memory_reserved_MB": 200.0, "f1_macro_score_only_mask_connect": -100.0, "f1_macro_score_only_not_mask_connect": -100.0, "f1_macro_score_mixed_connect": -100.0, "only_mask_connect_sum": -100.0, "only_not_mask_connect_sum": -100.0, "mixed_connect_sum": -100.0, "model_name": "GL_GINConv_9l_512h"}