{"f1_macro": 0.2824980978072906, "f1_weighted": 0.3865886197465363, "precision_macro": 0.2560817512424938, "precision_weighted": 0.3503520066526632, "recall_macro": 0.34116070358982553, "recall_weighted": 0.46702702702702703, "accuracy": 0.46702702702702703, "class_scores": {"Southern Russians": 0.5168776371308017, "Ukranians": 0.0, "Northen Russians": 0.6131147540983607, "Belarusians": 0.0}, "skipped_nodes": 0, "memory_allocated_MB": 29.59033203125, "memory_reserved_MB": 190.0, "f1_macro_score_only_mask_connect": 0.11904761904761904, "f1_macro_score_only_not_mask_connect": 0.0, "f1_macro_score_mixed_connect": 0.28362587665144945, "only_mask_connect_sum": 16.0, "only_not_mask_connect_sum": 1.0, "mixed_connect_sum": 908.0, "model_name": "GL_GCNConv_9l_128h_w"}