{"f1_macro": 0.8341743614994496, "f1_weighted": 0.9159750019352557, "precision_macro": 0.894633358662614, "precision_weighted": 0.9226585687466474, "recall_macro": 0.8115028133894502, "recall_weighted": 0.9220588235294118, "accuracy": 0.9220588235294118, "class_scores": {"English": 0.9739696312364425, "Germans": 0.8165137614678899, "French": 0.6265060240963856, "Belgium": 0.9197080291970803}, "skipped_nodes": 89, "memory_allocated_MB": 21.90771484375, "memory_reserved_MB": 84.0, "f1_macro_score_only_mask_connect": 0.680788367061071, "f1_macro_score_only_not_mask_connect": 0.818839336763865, "f1_macro_score_mixed_connect": 0.9525827992800795, "only_mask_connect_sum": 145.0, "only_not_mask_connect_sum": 74.0, "mixed_connect_sum": 461.0, "model_name": "GL_GCNConv_3l_512h_w"}