{"f1_macro": 0.4800870186375739, "f1_weighted": 0.7558908334817376, "precision_macro": 0.6954697986577181, "precision_weighted": 0.8164964795981389, "recall_macro": 0.42676767676767674, "recall_weighted": 0.8006134969325154, "accuracy": 0.8006134969325154, "class_scores": {"Udmurts,Besermyan": 0.56, "Tatars,Volga-Tatars,Mishar-Tatars,Kryashens": 0.8775894538606404, "Chuvash": 0.4827586206896552, "Mari": 0.0}, "skipped_nodes": 0, "memory_allocated_MB": 21.36328125, "memory_reserved_MB": 380.0, "model_name": "GL_GCNConv_3l_512h_w"}