{"f1_macro": 0.8701656781959096, "f1_weighted": 0.895975944212028, "precision_macro": 0.9182708581688669, "precision_weighted": 0.9043790498688008, "recall_macro": 0.8429081387212456, "recall_weighted": 0.8995215311004785, "accuracy": 0.8995215311004785, "class_scores": {"Swedes": 0.9103448275862069, "Norwegians": 0.9223744292237442, "Danes": 0.7777777777777778}, "skipped_nodes": 6, "memory_allocated_MB": 18.9990234375, "memory_reserved_MB": 72.0, "f1_macro_score_only_mask_connect": 0.8412698412698413, "f1_macro_score_only_not_mask_connect": 0.5978431372549019, "f1_macro_score_mixed_connect": 0.896913271913272, "only_mask_connect_sum": 6.0, "only_not_mask_connect_sum": 25.0, "mixed_connect_sum": 178.0, "model_name": "GL_GCNConv_9l_128h_w"}