{"f1_macro": 0.5169287770373385, "f1_weighted": 0.5732155908725055, "precision_macro": 0.5340691076048615, "precision_weighted": 0.5706804076834705, "recall_macro": 0.5126797952298167, "recall_weighted": 0.585945945945946, "accuracy": 0.585945945945946, "class_scores": {"Southern Russians": 0.6120058565153733, "Ukranians": 0.3849056603773585, "Northen Russians": 0.724812030075188, "Belarusians": 0.3459915611814346}, "skipped_nodes": 0, "memory_allocated_MB": 44.29248046875, "memory_reserved_MB": 228.0, "f1_macro_score_only_mask_connect": 0.6103896103896104, "f1_macro_score_only_not_mask_connect": 0.3333333333333333, "f1_macro_score_mixed_connect": 0.5126174989156225, "only_mask_connect_sum": 16.0, "only_not_mask_connect_sum": 6.0, "mixed_connect_sum": 903.0, "model_name": "GL_TAGConv_3l_512h_w_k3_gnorm"}