{"f1_macro": 0.856362681385048, "f1_weighted": 0.9262246158861764, "precision_macro": 0.9143874681663837, "precision_weighted": 0.9323480101178028, "recall_macro": 0.8280421576135113, "recall_weighted": 0.9301634472511144, "accuracy": 0.9301634472511144, "class_scores": {"English": 0.975929978118162, "Germans": 0.8202764976958525, "French": 0.6746987951807228, "Belgium": 0.9545454545454546}, "skipped_nodes": 96, "memory_allocated_MB": 17.3994140625, "memory_reserved_MB": 52.0, "f1_macro_score_only_mask_connect": 0.7028880076336547, "f1_macro_score_only_not_mask_connect": 0.990180978051598, "f1_macro_score_mixed_connect": 0.9182068969452147, "only_mask_connect_sum": 138.0, "only_not_mask_connect_sum": 72.0, "mixed_connect_sum": 463.0, "model_name": "GL_SAGEConv_3l_128h"}