{"f1_macro": 0.132579185520362, "f1_weighted": 0.18172089879829817, "precision_macro": 0.19319950202303143, "precision_weighted": 0.26437664555311613, "recall_macro": 0.251584774188396, "recall_weighted": 0.34486486486486484, "accuracy": 0.34486486486486484, "class_scores": {"Southern Russians": 0.5117408906882591, "Ukranians": 0.0, "Northen Russians": 0.018575851393188854, "Belarusians": 0.0}, "skipped_nodes": 0, "memory_allocated_MB": 343.416015625, "memory_reserved_MB": 8262.0, "f1_macro_score_only_mask_connect": -100.0, "f1_macro_score_only_not_mask_connect": -100.0, "f1_macro_score_mixed_connect": -100.0, "only_mask_connect_sum": -100.0, "only_not_mask_connect_sum": -100.0, "mixed_connect_sum": -100.0, "model_name": "GL_GATConv_9l_512h"}