{"f1_macro": 0.13610158528697477, "f1_weighted": 0.18653079918741794, "precision_macro": 0.16476414546299523, "precision_weighted": 0.22551907780907432, "recall_macro": 0.2500149742442998, "recall_weighted": 0.3427027027027027, "accuracy": 0.3427027027027027, "class_scores": {"Southern Russians": 0.508585445625511, "Ukranians": 0.0, "Northen Russians": 0.03582089552238806, "Belarusians": 0.0}, "skipped_nodes": 0, "memory_allocated_MB": 43.69189453125, "memory_reserved_MB": 870.0, "f1_macro_score_only_mask_connect": 0.25, "f1_macro_score_only_not_mask_connect": 0.2222222222222222, "f1_macro_score_mixed_connect": 0.13212132398178908, "only_mask_connect_sum": 16.0, "only_not_mask_connect_sum": 4.0, "mixed_connect_sum": 905.0, "model_name": "GL_GATConv_9l_128h"}