{"f1_macro": 0.31050693665415424, "f1_weighted": 0.39877351632561536, "precision_macro": 0.36607730263157895, "precision_weighted": 0.5066955741626794, "recall_macro": 0.3707298136645963, "recall_weighted": 0.4727272727272727, "accuracy": 0.4727272727272727, "class_scores": {"Chechens": 0.6181818181818182, "Kabardians, Circassians, Adyghes": 0.1875, "Karachays, Balkars": 0.6938775510204082, "Ingush": 0.0, "Dagestan peoples": 0.6511627906976745, "Ossetians": 0.0, "Kumyks": 0.0, "Nogais": 0.3333333333333333}, "skipped_nodes": 8, "memory_allocated_MB": 102.7197265625, "memory_reserved_MB": 150.0, "f1_macro_score_only_mask_connect": 0.31666666666666665, "f1_macro_score_only_not_mask_connect": 0.5599999999999999, "f1_macro_score_mixed_connect": 0.2790764790764791, "only_mask_connect_sum": 21.0, "only_not_mask_connect_sum": 8.0, "mixed_connect_sum": 81.0, "model_name": "GL_GINConv_9l_512h"}