{"f1_macro": 0.8763541946458949, "f1_weighted": 0.9005248042314924, "precision_macro": 0.9355044699872286, "precision_weighted": 0.9119326554671381, "recall_macro": 0.8449846652164221, "recall_weighted": 0.9038461538461539, "accuracy": 0.9038461538461539, "class_scores": {"Swedes": 0.9315068493150684, "Norwegians": 0.91324200913242, "Danes": 0.7843137254901961}, "skipped_nodes": 7, "memory_allocated_MB": 25.6728515625, "memory_reserved_MB": 82.0, "f1_macro_score_only_mask_connect": 0.8222222222222223, "f1_macro_score_only_not_mask_connect": 0.7380952380952381, "f1_macro_score_mixed_connect": 0.8944221628045158, "only_mask_connect_sum": 5.0, "only_not_mask_connect_sum": 19.0, "mixed_connect_sum": 184.0, "model_name": "GL_TAGConv_9l_128h_w_k3"}