{"f1_macro": 0.8874235111246718, "f1_weighted": 0.9718356538587745, "precision_macro": 0.8625, "precision_weighted": 0.9848159509202454, "recall_macro": 0.966478085576798, "recall_weighted": 0.9662576687116564, "accuracy": 0.9662576687116564, "class_scores": {"Udmurts,Besermyan": 1.0, "Tatars,Volga-Tatars,Mishar-Tatars,Kryashens": 0.9935205183585313, "Chuvash": 0.9354838709677419, "Mari": 0.6206896551724138}, "skipped_nodes": 0, "memory_allocated_MB": 19.1005859375, "memory_reserved_MB": 106.0, "model_name": "GL_GINConv_3l_128h"}