{"f1_macro": 0.3253325744748078, "f1_weighted": 0.4179715691467883, "precision_macro": 0.33004575072550635, "precision_weighted": 0.41954725364588985, "recall_macro": 0.36163967888651427, "recall_weighted": 0.47122692725298587, "accuracy": 0.47122692725298587, "class_scores": {"Southern Russians": 0.5567685589519651, "Ukranians": 0.0, "Northen Russians": 0.6048237476808905, "Belarusians": 0.13973799126637554}, "skipped_nodes": 4, "memory_allocated_MB": 26.03271484375, "memory_reserved_MB": 104.0, "f1_macro_score_only_mask_connect": 0.041666666666666664, "f1_macro_score_only_not_mask_connect": 0.30677655677655674, "f1_macro_score_mixed_connect": 0.3074758404567326, "only_mask_connect_sum": 12.0, "only_not_mask_connect_sum": 35.0, "mixed_connect_sum": 874.0, "model_name": "GL_GINConv_9l_128h"}