{"f1_macro": 0.2501164551065564, "f1_weighted": 0.1911864203343476, "precision_macro": 0.2583955223880597, "precision_weighted": 0.20338110063181028, "recall_macro": 0.4696969696969697, "recall_weighted": 0.20552147239263804, "accuracy": 0.20552147239263804, "class_scores": {"Udmurts,Besermyan": 0.0, "Tatars,Volga-Tatars,Mishar-Tatars,Kryashens": 0.0, "Chuvash": 0.9354838709677419, "Mari": 0.06498194945848375}, "skipped_nodes": 0, "memory_allocated_MB": 25.50146484375, "memory_reserved_MB": 230.0, "model_name": "GL_GINConv_9l_128h"}