{"f1_macro": 0.7353218031398605, "f1_weighted": 0.8350527481494434, "precision_macro": 0.7422498355402767, "precision_weighted": 0.863955975798081, "recall_macro": 0.744453781512605, "recall_weighted": 0.8245614035087719, "accuracy": 0.8245614035087719, "class_scores": {"Chechens": 0.8823529411764706, "Kabardians, Circassians, Adyghes": 0.8666666666666667, "Karachays, Balkars": 0.8666666666666667, "Ingush": 0.9523809523809523, "Dagestan peoples": 0.7906976744186046, "Ossetians": 0.8571428571428571, "Kumyks": 0.0, "Nogais": 0.6666666666666666}, "skipped_nodes": 4, "memory_allocated_MB": 28.44384765625, "memory_reserved_MB": 118.0, "f1_macro_score_only_mask_connect": 0.3213507625272331, "f1_macro_score_only_not_mask_connect": 0.76, "f1_macro_score_mixed_connect": 0.794796031056807, "only_mask_connect_sum": 25.0, "only_not_mask_connect_sum": 7.0, "mixed_connect_sum": 82.0, "model_name": "GL_SAGEConv_3l_512h_de"}