{"f1_macro": 0.13584527758653064, "f1_weighted": 0.18599963341127357, "precision_macro": 0.21125410733844469, "precision_weighted": 0.28875968762274545, "recall_macro": 0.2531771147277476, "recall_weighted": 0.3466955579631636, "accuracy": 0.3466955579631636, "class_scores": {"Southern Russians": 0.5126118795768918, "Ukranians": 0.0, "Northen Russians": 0.03076923076923077, "Belarusians": 0.0}, "skipped_nodes": 2, "memory_allocated_MB": 41.01513671875, "memory_reserved_MB": 806.0, "f1_macro_score_only_mask_connect": 0.11764705882352941, "f1_macro_score_only_not_mask_connect": 0.09523809523809523, "f1_macro_score_mixed_connect": 0.13651918047079337, "only_mask_connect_sum": 14.0, "only_not_mask_connect_sum": 29.0, "mixed_connect_sum": 880.0, "model_name": "GL_GATConv_9l_128h"}