{"f1_macro": 0.279652358478129, "f1_weighted": 0.38263712865184113, "precision_macro": 0.2353619082349201, "precision_weighted": 0.3220381098088748, "recall_macro": 0.34449247294653196, "recall_weighted": 0.47135135135135137, "accuracy": 0.47135135135135137, "class_scores": {"Southern Russians": 0.4587628865979381, "Ukranians": 0.0, "Northen Russians": 0.659846547314578, "Belarusians": 0.0}, "skipped_nodes": 0, "memory_allocated_MB": 53.130859375, "memory_reserved_MB": 546.0, "model_name": "GL_GCNConv_9l_512h_w"}