{"f1_macro": 0.9420181803408698, "f1_weighted": 0.9626758506048262, "precision_macro": 0.9473595609100327, "precision_weighted": 0.9631603458988494, "recall_macro": 0.9378669601325791, "recall_weighted": 0.9626556016597511, "accuracy": 0.9626556016597511, "class_scores": {"English": 0.9837133550488599, "Germans": 0.9182879377431906, "French": 0.9375, "Belgium": 0.9285714285714286}, "skipped_nodes": 46, "memory_allocated_MB": 44.24560546875, "memory_reserved_MB": 218.0, "f1_macro_score_only_mask_connect": -100.0, "f1_macro_score_only_not_mask_connect": -100.0, "f1_macro_score_mixed_connect": -100.0, "only_mask_connect_sum": -100.0, "only_not_mask_connect_sum": -100.0, "mixed_connect_sum": -100.0, "model_name": "GL_TAGConv_3l_512h_nw_k3_gnorm_leaky_relu"}