{"f1_macro": 0.8368107782417239, "f1_weighted": 0.9171240969807131, "precision_macro": 0.885944925865847, "precision_weighted": 0.9205788321969814, "recall_macro": 0.8136173722111222, "recall_weighted": 0.9228486646884273, "accuracy": 0.9228486646884273, "class_scores": {"English": 0.9759825327510917, "Germans": 0.8095238095238095, "French": 0.6363636363636364, "Belgium": 0.9253731343283582}, "skipped_nodes": 95, "memory_allocated_MB": 18.1396484375, "memory_reserved_MB": 58.0, "f1_macro_score_only_mask_connect": 0.6694710260499734, "f1_macro_score_only_not_mask_connect": 0.8482029598308668, "f1_macro_score_mixed_connect": 0.9576641767818238, "only_mask_connect_sum": 139.0, "only_not_mask_connect_sum": 67.0, "mixed_connect_sum": 468.0, "model_name": "GL_TAGConv_3l_128h_w_k3"}