{"f1_macro": 0.4166150142381042, "f1_weighted": 0.5100135595211996, "precision_macro": 0.43741081679514515, "precision_weighted": 0.5006316221092341, "recall_macro": 0.4455761090923611, "recall_weighted": 0.5664864864864865, "accuracy": 0.5664864864864865, "class_scores": {"Southern Russians": 0.5997610513739546, "Ukranians": 0.3508771929824561, "Northen Russians": 0.7158218125960062, "Belarusians": 0.0}, "skipped_nodes": 0, "memory_allocated_MB": 32.27978515625, "memory_reserved_MB": 122.0, "f1_macro_score_only_mask_connect": 0.3923611111111111, "f1_macro_score_only_not_mask_connect": 0.39285714285714285, "f1_macro_score_mixed_connect": 0.4080837951644373, "only_mask_connect_sum": 16.0, "only_not_mask_connect_sum": 8.0, "mixed_connect_sum": 901.0, "model_name": "GL_TAGConv_9l_128h_w_k3"}