{"f1_macro": 0.8441069513330133, "f1_weighted": 0.9317423223887982, "precision_macro": 0.9009254511338194, "precision_weighted": 0.9368436816408178, "recall_macro": 0.8176100058756893, "recall_weighted": 0.9352290679304898, "accuracy": 0.9352290679304898, "class_scores": {"English": 0.9819004524886877, "Germans": 0.8350515463917526, "French": 0.65625, "Belgium": 0.9032258064516129}, "skipped_nodes": 136, "memory_allocated_MB": 51.8115234375, "memory_reserved_MB": 128.0, "f1_macro_score_only_mask_connect": 0.6893136907573609, "f1_macro_score_only_not_mask_connect": 0.9058190692748105, "f1_macro_score_mixed_connect": 0.8348842348333352, "only_mask_connect_sum": 98.0, "only_not_mask_connect_sum": 166.0, "mixed_connect_sum": 369.0, "model_name": "GL_GCNConv_9l_512h_w"}