{"f1_macro": 0.2936827557019197, "f1_weighted": 0.4017478389688598, "precision_macro": 0.2478267400161469, "precision_weighted": 0.33901839759784597, "recall_macro": 0.36075949367088606, "recall_weighted": 0.4935064935064935, "accuracy": 0.4935064935064935, "class_scores": {"Southern Russians": 0.5388471177944862, "Ukranians": 0.0, "Northen Russians": 0.6358839050131926, "Belarusians": 0.0}, "skipped_nodes": 1, "memory_allocated_MB": 22.72802734375, "memory_reserved_MB": 70.0, "f1_macro_score_only_mask_connect": 0.10526315789473684, "f1_macro_score_only_not_mask_connect": 0.3333333333333333, "f1_macro_score_mixed_connect": 0.2951411855794326, "only_mask_connect_sum": 15.0, "only_not_mask_connect_sum": 3.0, "mixed_connect_sum": 906.0, "model_name": "GL_SAGEConv_3l_128h_de"}