{"f1_macro": 0.3253334628334628, "f1_weighted": 0.5044557294557295, "precision_macro": 0.3244398656898657, "precision_weighted": 0.516591662305948, "recall_macro": 0.3935619506423259, "recall_weighted": 0.5446428571428571, "accuracy": 0.5446428571428571, "class_scores": {"Chechens": 0.0, "Kabardians, Circassians, Adyghes": 0.8518518518518519, "Karachays, Balkars": 0.7333333333333333, "Ingush": 0.36363636363636365, "Dagestan peoples": 0.6538461538461539, "Ossetians": 0.0, "Kumyks": 0.0, "Nogais": 0.0}, "skipped_nodes": 6, "memory_allocated_MB": 16.619140625, "memory_reserved_MB": 56.0, "model_name": "GL_GCNConv_3l_128h_w"}