{"f1_macro": 0.6128494703966402, "f1_weighted": 0.6894399181837564, "precision_macro": 0.689731334841629, "precision_weighted": 0.8321036647507236, "recall_macro": 0.6787655279503105, "recall_weighted": 0.6936936936936937, "accuracy": 0.6936936936936937, "class_scores": {"Chechens": 0.3, "Kabardians, Circassians, Adyghes": 0.8679245283018868, "Karachays, Balkars": 0.8484848484848485, "Ingush": 0.5555555555555556, "Dagestan peoples": 0.7567567567567568, "Ossetians": 0.7407407407407407, "Kumyks": 0.5, "Nogais": 0.3333333333333333}, "skipped_nodes": 7, "memory_allocated_MB": 341.99462890625, "memory_reserved_MB": 700.0, "f1_macro_score_only_mask_connect": 0.2875, "f1_macro_score_only_not_mask_connect": 0.5037037037037037, "f1_macro_score_mixed_connect": 0.6369172632396066, "only_mask_connect_sum": 22.0, "only_not_mask_connect_sum": 11.0, "mixed_connect_sum": 78.0, "model_name": "GL_GATConv_9l_512h"}