{"f1_macro": 0.8079503992268168, "f1_weighted": 0.9575678588216978, "precision_macro": 0.8880876068376068, "precision_weighted": 0.9588970164123537, "recall_macro": 0.7846599037586162, "recall_weighted": 0.9631901840490797, "accuracy": 0.9631901840490797, "class_scores": {"Udmurts,Besermyan": 0.9714285714285714, "Tatars,Volga-Tatars,Mishar-Tatars,Kryashens": 0.9850107066381156, "Chuvash": 0.9420289855072463, "Mari": 0.3333333333333333}, "skipped_nodes": 0, "memory_allocated_MB": 100.31298828125, "memory_reserved_MB": 584.0, "f1_macro_score_only_mask_connect": NaN, "f1_macro_score_only_not_mask_connect": 0.8079503992268168, "f1_macro_score_mixed_connect": NaN, "only_mask_connect_sum": 0.0, "only_not_mask_connect_sum": 326.0, "mixed_connect_sum": 0.0, "model_name": "GL_GATConv_3l_512h"}