{"f1_macro": 0.6272634889050757, "f1_weighted": 0.7862309169549188, "precision_macro": 0.6285665990534145, "precision_weighted": 0.8069290826284972, "recall_macro": 0.6418148028442145, "recall_weighted": 0.7924528301886793, "accuracy": 0.7924528301886793, "class_scores": {"Chechens": 0.8571428571428571, "Kabardians, Circassians, Adyghes": 0.7906976744186046, "Karachays, Balkars": 0.9411764705882353, "Ingush": 0.9090909090909091, "Dagestan peoples": 0.72, "Ossetians": 0.8, "Kumyks": 0.0, "Nogais": 0.0}, "skipped_nodes": 12, "memory_allocated_MB": 22.23974609375, "memory_reserved_MB": 76.0, "f1_macro_score_only_mask_connect": 0.14583333333333334, "f1_macro_score_only_not_mask_connect": 0.35402097902097907, "f1_macro_score_mixed_connect": 0.6936774916113372, "only_mask_connect_sum": 17.0, "only_not_mask_connect_sum": 19.0, "mixed_connect_sum": 70.0, "model_name": "GL_MLP_3l_512h"}