{"f1_macro": 0.3395696298578478, "f1_weighted": 0.4559463411276682, "precision_macro": 0.4853242720575775, "precision_weighted": 0.5268417978644062, "recall_macro": 0.4011040375633276, "recall_weighted": 0.5443722943722944, "accuracy": 0.5443722943722944, "class_scores": {"Southern Russians": 0.571103526734926, "Ukranians": 0.049079754601226995, "Northen Russians": 0.7380952380952381, "Belarusians": 0.0}, "skipped_nodes": 1, "memory_allocated_MB": 27.7109375, "memory_reserved_MB": 184.0, "f1_macro_score_only_mask_connect": 0.08333333333333333, "f1_macro_score_only_not_mask_connect": 0.0, "f1_macro_score_mixed_connect": 0.34280315521906846, "only_mask_connect_sum": 15.0, "only_not_mask_connect_sum": 2.0, "mixed_connect_sum": 907.0, "model_name": "GL_GCNConv_3l_128h_w"}